tree_sitter_languages/__init__.py
tree_sitter_languages/core.cpython-311-darwin.so
textual_tree_sitter_languages-0.0.0a0.dist-info/LICENSE
textual_tree_sitter_languages-0.0.0a0.dist-info/METADATA
textual_tree_sitter_languages-0.0.0a0.dist-info/WHEEL
textual_tree_sitter_languages-0.0.0a0.dist-info/top_level.txt
textual_tree_sitter_languages-0.0.0a0.dist-info/RECORD
