Metadata-Version: 2.1
Name: textual_tree_sitter_languages
Version: 0.0.0a0
Summary: Binary Python wheels for all tree sitter languages.
Home-page: https://github.com/Textualize/py-tree-sitter-languages
Author: Textualize
Author-email: will@textualize.io
License: Apache 2.0
Project-URL: Documentation, https://github.com/Textualize/py-tree-sitter-languages
Project-URL: Source, https://github.com/Textualize/py-tree-sitter-languages
Project-URL: Tracker, https://github.com/Textualize/py-tree-sitter-languages/issues
Classifier: Development Status :: 5 - Production/Stable
Classifier: Intended Audience :: Developers
Classifier: License :: OSI Approved :: Apache Software License
Classifier: Natural Language :: English
Classifier: Programming Language :: Python
Classifier: Programming Language :: Python :: 3
Classifier: Programming Language :: Python :: Implementation :: CPython
Requires-Python: >=3.8.1
License-File: LICENSE
Requires-Dist: tree-sitter<0.22.0
